remote_builder
